{
  "activityName": "Cocoa powder, consumption mix {FR} U",
  "categories": [
    "ingredient",
    "material",
    "material_type:other_food_items"
  ],
  "displayName": "Poudre de cacao UE",
  "id": "cd4ce74c-2c6e-55e1-a72f-062614a59553",
  "metadata": [
    {
      "alias": "cocoa-powder-ue-2025",
      "cropGroup": "FRUITS A COQUES",
      "defaultOrigin": "EuropeAndMaghreb",
      "displayName": "Poudre de cacao UE (2025)",
      "explain": "avion à vérifier",
      "id": "88bd8bf2-0e2f-4adf-98cf-09325e38b7f9",
      "inediblePart": 0,
      "ingredientCategories": [
        "vegetable_processed"
      ],
      "ingredientDensity": 0.24,
      "landOccupation": 11.9277,
      "rawToCookedRatio": 1.0,
      "scenario": "import",
      "scopes": [
        "food",
        "food2"
      ],
      "transportCooling": "none",
      "visible": true
    },
    {
      "alias": "cocoa-powder-non-ue-2025",
      "cropGroup": "FRUITS A COQUES",
      "defaultOrigin": "OutOfEuropeAndMaghrebByPlane",
      "displayName": "Poudre de cacao par défaut (2025)",
      "explain": "avion à vérifier",
      "id": "3d7f808b-77c5-4207-968d-feea6dfd9496",
      "inediblePart": 0,
      "ingredientCategories": [
        "vegetable_processed"
      ],
      "ingredientDensity": 0.24,
      "rawToCookedRatio": 1.0,
      "scenario": "import",
      "scopes": [
        "food",
        "food2"
      ],
      "transportCooling": "none",
      "visible": true
    }
  ],
  "scopes": [
    "food",
    "food2"
  ],
  "source": "Agribalyse 3.2"
}
