{
  "activityName": "Egg, conventional, indoor system, cage, at farm gate {FR} U",
  "categories": [
    "ingredient",
    "material",
    "material_type:eggs"
  ],
  "displayName": "Oeuf (code 3) FR",
  "id": "5bad1f5e-34de-57aa-827b-afeda19f8fe5",
  "metadata": [
    {
      "alias": "egg-indoor-code3-2025",
      "animalGroup1": "poultry",
      "animalGroup2": "chicken",
      "animalProduct": "egg",
      "defaultOrigin": "France",
      "displayName": "Oeuf (code 3) FR (2025)",
      "id": "9cbc31e9-80a4-4b87-ac4b-ddc051c47f69",
      "inediblePart": 0.2,
      "ingredientCategories": [
        "animal_product"
      ],
      "ingredientDensity": 1.0,
      "rawToCookedRatio": 0.974,
      "scenario": "reference",
      "scopes": [
        "food",
        "food2"
      ],
      "transportCooling": "none",
      "visible": false
    }
  ],
  "scopes": [
    "food",
    "food2"
  ],
  "source": "Agribalyse 3.2"
}
