{
  "activityName": "Egg yolk, powder, at plant {FR} U",
  "categories": [
    "ingredient",
    "material",
    "material_type:other_food_items"
  ],
  "displayName": "poudre de jaune d'oeuf FR",
  "id": "59c5e707-db3b-5ed7-b6c1-a97a1e2a369e",
  "metadata": [
    {
      "alias": "egg-yolk-powder-fr-2025",
      "animalGroup1": "poultry",
      "animalGroup2": "chicken",
      "animalProduct": "egg",
      "defaultOrigin": "France",
      "displayName": "poudre de jaune d'oeuf FR (2025)",
      "explain": "mélange de jaune d'oeuf et de poudre de lactoserum",
      "id": "f6e84334-a8bb-4f07-915d-ef51e8dcf800",
      "inediblePart": 0,
      "ingredientCategories": [
        "animal_product"
      ],
      "ingredientDensity": 0.24,
      "rawToCookedRatio": 1.0,
      "scenario": "reference",
      "scopes": [
        "food",
        "food2"
      ],
      "transportCooling": "once_transformed",
      "visible": true
    }
  ],
  "scopes": [
    "food",
    "food2"
  ],
  "source": "Agribalyse 3.2"
}
