{
  "activityName": "Olive {IT}| olive production | Cut-off, U - Copied from Ecoinvent U",
  "categories": [
    "ingredient",
    "material",
    "material_type:fruits_and_vegetables"
  ],
  "displayName": "Olive (IT)",
  "id": "1d78be36-89e7-5178-9bae-011b6e1ecf01",
  "metadata": [
    {
      "alias": "olive-eu",
      "cropGroup": "OLIVIERS",
      "cropGroupMatch": {
        "confidence": 0.95,
        "rule": "matched 'olive' in cropgroup.csv"
      },
      "defaultOrigin": "EuropeAndMaghreb",
      "displayName": "Olives UE",
      "id": "c3519237-1565-5c43-b47c-a8cc2e002540",
      "inediblePart": 0.5,
      "inediblePartMatch": {
        "confidence": 1.0,
        "rule": "Matched with Olives in agb_inedible.csv"
      },
      "ingredientCategories": [
        "vegetable_fresh"
      ],
      "ingredientDensity": 0.65,
      "ingredientDensityMatch": {
        "confidence": 0.95,
        "rule": "Matched with Olives, green, with stone in fao_density.csv"
      },
      "rawToCookedRatio": 0.856,
      "rawToCookedRatioMatch": {
        "confidence": 1.0,
        "rule": "fruit default from food_type_cooked_to_raw.csv"
      },
      "scenario": "import",
      "scopes": [
        "food",
        "food2"
      ],
      "transportCooling": "always",
      "transportCoolingMatch": {
        "confidence": 1.0,
        "rule": "fruit NOVA 1 → always (perishable)"
      },
      "visible": true
    }
  ],
  "scopes": [
    "food",
    "food2"
  ],
  "source": "Agribalyse 3.2",
  "unit": "kg"
}
