{
  "activityName": "Coconut, dehusked, at farm (WFLDB)",
  "categories": [
    "ingredient",
    "material",
    "material_type:other_food_items"
  ],
  "displayName": "Noix de coco décortiquée Origine Inconnue",
  "id": "9aa655c2-6efe-56d0-b4c1-a14403b17ecd",
  "location": "PH",
  "metadata": [
    {
      "alias": "coconut-dehusked-default",
      "cropGroup": "FRUITS A COQUES",
      "cropGroupMatch": {
        "confidence": 1.0,
        "rule": "nut default"
      },
      "defaultOrigin": "OutOfEuropeAndMaghreb",
      "displayName": "Noix de coco décortiquée Origine Inconnue",
      "id": "c8c1ff4e-fe84-5a77-9ba8-7a988895c2d5",
      "inediblePart": 0.5,
      "inediblePartMatch": {
        "confidence": 1.0,
        "rule": "nut_oilseed NOVA 1 default from food_type_inedible_part.csv"
      },
      "ingredientCategories": [
        "nut_oilseed_raw"
      ],
      "ingredientDensity": 0.5,
      "ingredientDensityMatch": {
        "confidence": 0.95,
        "rule": "Matched with coconut in density.csv"
      },
      "rawToCookedRatio": 1.0,
      "rawToCookedRatioMatch": {
        "confidence": 1.0,
        "rule": "nut_oilseed default from food_type_cooked_to_raw.csv"
      },
      "scenario": "import",
      "scopes": [
        "food",
        "food2"
      ],
      "transportCooling": "none",
      "transportCoolingMatch": {
        "confidence": 1.0,
        "rule": "nut_oilseed → none (non-perishable)"
      },
      "visible": true
    }
  ],
  "scopes": [
    "food",
    "food2"
  ],
  "source": "WFLDB",
  "unit": "kg"
}
