{
  "activityName": "French bean, frozen, at processing {FR} U [french-bean-organic] {{french-bean-frozen-organic}}",
  "categories": [
    "ingredient",
    "material"
  ],
  "displayName": "Haricots, congelés Bio",
  "id": "80633b0b-1d73-4d0c-bad8-b51690444279",
  "metadata": [
    {
      "alias": "french-bean-frozen-organic",
      "cropGroup": "LEGUMINEUSES A GRAIN",
      "defaultOrigin": "France",
      "displayName": "Haricots, congelés Bio",
      "id": "38bdabfc-26ec-4fbb-9e71-af7a39dce6b3",
      "inediblePart": 0,
      "ingredientCategories": [
        "vegetable_processed",
        "organic"
      ],
      "ingredientDensity": 0.8,
      "rawToCookedRatio": 1.0,
      "scenario": "organic",
      "scopes": [
        "food",
        "food2"
      ],
      "transportCooling": "always",
      "visible": true
    }
  ],
  "scopes": [
    "food",
    "food2"
  ],
  "source": "Ecobalyse"
}
